{
	"pizza": [
		{
			"pizzaName": "Цыпленок карри",
			"img": "../src/img/pizza/1.webp",
			"smallImg": "src/img/pizza/1-s.webp",
			"bigImg": "src/img/pizza/1-b.webp",
			"alt": "Цыпленок карри",
			"price": "24.90",
			"smallPrice": "17.90",
			"bigPrice": "28.90",
			"size": "30 см",
			"smallSize": "25 см",
			"bigSize": "35 см",
			"smallWeight": "410",
			"weight": "630",
			"bigWeight": "875",
			"ingridient": "Цыпленок, ананасы, соус карри, красный лук, сладкий перец, моцарелла, томатный соус",
			"dataIngridient": "onion pepper meet",
			"id": "ChikenCarri"
		},
		{
			"pizzaName": "Индейка песто",
			"img": "src/img/pizza/2.webp",
			"smallImg": "src/img/pizza/2-s.webp",
			"bigImg": "src/img/pizza/2-b.webp",
			"alt": "Индейка песто",
			"price": "27.90",
			"smallPrice": "20.90",
			"bigPrice": "31.90",
			"size": "30 см",
			"smallSize": "25 см",
			"bigSize": "35 см",
			"smallWeight": "450",
			"weight": "605",
			"bigWeight": "900",
			"ingridient": "Соус песто, пастрами из индейки, кубики брынзы, сладкий перец, красный лук, моцарелла, томатный соус",
			"dataIngridient": "onion pepper meet",
			"id": "TurkeyPesto"
		},
		{
			"pizzaName": "Мясной Микс",
			"img": "src/img/pizza/3.webp",
			"smallImg": "src/img/pizza/3-s.webp",
			"bigImg": "src/img/pizza/3-b.webp",
			"alt": "Мясной Микс",
			"price": "29.90",
			"smallPrice": "20.90",
			"bigPrice": "32.90",
			"size": "30 см",
			"smallSize": "25 см",
			"bigSize": "35 см",
			"smallWeight": "360",
			"weight": "560",
			"bigWeight": "720",
			"ingridient": "Пастрами из индейки, острые колбаски чоризо, пикантная пепперони, бекон, моцарелла, томатный соус",
			"dataIngridient": "meet",
			"id": "MeetMix"
		},
		{
			"pizzaName": "Белая пепперони",
			"img": "src/img/pizza/4.webp",
			"smallImg": "src/img/pizza/4-s.webp",
			"bigImg": "src/img/pizza/4-b.webp",
			"alt": "Белая пепперони",
			"price": "20.90",
			"smallPrice": "13.90",
			"bigPrice": "26.90",
			"size": "30 см",
			"smallSize": "25 см",
			"bigSize": "35 см",
			"smallWeight": "310",
			"weight": "490",
			"bigWeight": "620",
			"ingridient": "Пикантная пепперони, соус альфредо, моцарелла",
			"dataIngridient": "meet",
			"id": "WhitePepperoni"
		},
		{
			"pizzaName": "Дон Бекон",
			"img": "src/img/pizza/5.webp",
			"smallImg": "src/img/pizza/5-s.webp",
			"bigImg": "src/img/pizza/5-b.webp",
			"alt": "Дон Бекон",
			"price": "28.40",
			"smallPrice": "20.90",
			"bigPrice": "32.40",
			"size": "30 см",
			"smallSize": "25 см",
			"bigSize": "35 см",
			"smallWeight": "420",
			"weight": "620",
			"bigWeight": "830",
			"ingridient": "Томатный соус, цыпленок филе, пикантная пепперони, красный лук, моцарелла, бекон",
			"dataIngridient": "onion meet",
			"id": "DonBecon"
		},
		{
			"pizzaName": "Четыре сезона",
			"img": "src/img/pizza/6.webp",
			"smallImg": "src/img/pizza/6-s.webp",
			"bigImg": "src/img/pizza/6-b.webp",
			"alt": "Четыре сезона",
			"price": "25.40",
			"smallPrice": "17.90",
			"bigPrice": "29.40",
			"size": "30 см",
			"smallSize": "25 см",
			"bigSize": "35 см",
			"smallWeight": "440",
			"weight": "660",
			"bigWeight": "900",
			"ingridient": "Итальянские травы, томатный соус, томаты, пикантная пепперони, кубики брынзы, моцарелла, ветчина, шампиньоны",
			"dataIngridient": "meet tomato mushrooms",
			"id": "FourSeasons"
		},
		{
			"pizzaName": "Карбонара",
			"img": "src/img/pizza/7.webp",
			"smallImg": "src/img/pizza/7-s.webp",
			"bigImg": "src/img/pizza/7-b.webp",
			"alt": "Карбонара",
			"price": "25.40",
			"smallPrice": "17.90",
			"bigPrice": "29.40",
			"size": "30 см",
			"smallSize": "25 см",
			"bigSize": "35 см",
			"smallWeight": "410",
			"weight": "620",
			"bigWeight": "860",
			"ingridient": "Бекон, сыры чеддер и пармезан, моцарелла, томаты, соус альфредо, красный лук, чеснок, итальянские травы",
			"dataIngridient": "meet tomato onion garlic",
			"id": "Carbonara"
		},
		{
			"pizzaName": "Деревенская",
			"img": "src/img/pizza/8.webp",
			"smallImg": "src/img/pizza/8-s.webp",
			"bigImg": "src/img/pizza/8-b.webp",
			"alt": "Деревенская",
			"price": "25.40",
			"smallPrice": "17.90",
			"bigPrice": "29.40",
			"size": "30 см",
			"smallSize": "25 см",
			"bigSize": "35 см",
			"smallWeight": "555",
			"weight": "910",
			"bigWeight": "1 175",
			"ingridient": "Картофель из печи, маринованные огурчики, цыпленок, соус ранч, томаты, красный лук, чеснок, моцарелла, томатный соус",
			"dataIngridient": "meet tomato onion garlic potato",
			"id": "Villiagy"
		},
		{
			"pizzaName": "Ветчина и огурчики",
			"img": "src/img/pizza/9.webp",
			"smallImg": "src/img/pizza/9-s.webp",
			"bigImg": "src/img/pizza/9-b.webp",
			"alt": "Ветчина и огурчики",
			"price": "15.90",
			"smallPrice": "8.90",
			"bigPrice": "21.40",
			"size": "30 см",
			"smallSize": "25 см",
			"bigSize": "35 см",
			"smallWeight": "340",
			"weight": "510",
			"bigWeight": "680",
			"ingridient": "Ветчина, маринованные огурчики, красный лук",
			"dataIngridient": "meet onion cucumber",
			"id": "HamAndCucumbers"
		},
		{
			"pizzaName": "Бургер-пицца",
			"img": "src/img/pizza/10.webp",
			"smallImg": "src/img/pizza/10-s.webp",
			"bigImg": "src/img/pizza/10-b.webp",
			"alt": "Бургер-пицца",
			"price": "25.40",
			"smallPrice": "17.90",
			"bigPrice": "29.40",
			"size": "30 см",
			"smallSize": "25 см",
			"bigSize": "35 см",
			"smallWeight": "425",
			"weight": "630",
			"bigWeight": "840",
			"ingridient": "Томатный соус, моцарелла, ветчина, красный лук, томаты, маринованные огурчики, соус бургер, чеснок",
			"dataIngridient": "meet onion cucumber tomato garlic",
			"id": "Burger"
		},
		{
			"pizzaName": "Аррива!",
			"img": "src/img/pizza/11.webp",
			"smallImg": "src/img/pizza/11-s.webp",
			"bigImg": "src/img/pizza/11-b.webp",
			"alt": "Аррива!",
			"price": "25.40",
			"smallPrice": "17.90",
			"bigPrice": "29.40",
			"size": "30 см",
			"smallSize": "25 см",
			"bigSize": "35 см",
			"smallWeight": "405",
			"weight": "615",
			"bigWeight": "825",
			"ingridient": "Цыпленок, чоризо, соус бургер, томаты, сладкий перец, лук красный, чеснок, моцарелла, соус ранч",
			"dataIngridient": "meet onion papper tomato garlic",
			"id": "Arriva"
		}
	]
}